{"repo":{"name":"github.com/qemu/qemu","criticalityScore":0.8012,"criticality":102},"score":4.3,"checks":[{"name":"Maintained","score":10},{"name":"Code-Review"},{"name":"CII-Best-Practices"},{"name":"Signed-Releases","score":-1},{"name":"Vulnerabilities","score":8},{"name":"Branch-Protection"},{"name":"Dangerous-Workflow","score":10},{"name":"Token-Permissions","score":10},{"name":"License","score":10},{"name":"Packaging","score":-1},{"name":"Dependency-Update-Tool"},{"name":"SAST"},{"name":"Security-Policy"},{"name":"Fuzzing"},{"name":"Binary-Artifacts","score":2},{"name":"Pinned-Dependencies","score":5}]}