{"repo":{"name":"github.com/facebook/react-native","criticalityScore":0.849,"criticality":23},"score":5.1,"checks":[{"name":"Maintained","score":10},{"name":"Code-Review","score":10},{"name":"CII-Best-Practices"},{"name":"Vulnerabilities","score":10},{"name":"Signed-Releases"},{"name":"Branch-Protection","score":3},{"name":"Packaging","score":-1},{"name":"Token-Permissions"},{"name":"License","score":10},{"name":"Dangerous-Workflow","score":10},{"name":"SAST"},{"name":"Dependency-Update-Tool"},{"name":"Binary-Artifacts","score":5},{"name":"Fuzzing"},{"name":"Pinned-Dependencies","score":5},{"name":"Security-Policy","score":10}]}