{"repo":{"name":"github.com/postcss/autoprefixer","criticalityScore":0.73133,"criticality":648},"score":5.3,"checks":[{"name":"Maintained","score":10},{"name":"Code-Review","score":1},{"name":"CII-Best-Practices"},{"name":"Vulnerabilities","score":10},{"name":"Packaging","score":-1},{"name":"License","score":10},{"name":"Token-Permissions","score":10},{"name":"Dangerous-Workflow","score":10},{"name":"Pinned-Dependencies","score":7},{"name":"Binary-Artifacts","score":10},{"name":"Security-Policy"},{"name":"Dependency-Update-Tool"},{"name":"Fuzzing"},{"name":"SAST"},{"name":"Signed-Releases","score":-1},{"name":"Branch-Protection"}]}