{"repo":{"name":"github.com/zloirock/core-js","criticalityScore":0.7303,"criticality":662},"score":5.4,"checks":[{"name":"Maintained","score":10},{"name":"Code-Review"},{"name":"CII-Best-Practices"},{"name":"Vulnerabilities","score":10},{"name":"Signed-Releases","score":-1},{"name":"Branch-Protection"},{"name":"Token-Permissions"},{"name":"Security-Policy","score":10},{"name":"Dangerous-Workflow","score":10},{"name":"Packaging","score":-1},{"name":"License","score":10},{"name":"Pinned-Dependencies","score":9},{"name":"Binary-Artifacts","score":10},{"name":"Dependency-Update-Tool"},{"name":"SAST"},{"name":"Fuzzing","score":-1}]}